PVGeo/__init__.py
PVGeo/base.py
PVGeo/cmaps.py
PVGeo/interface.py
PVGeo/_helpers/__init__.py
PVGeo/_helpers/arrays.py
PVGeo/_helpers/errors.py
PVGeo/_helpers/readers.py
PVGeo/_helpers/timeseries.py
PVGeo/_helpers/xml.py
PVGeo/filters/__init__.py
PVGeo/filters/math.py
PVGeo/filters/slicing.py
PVGeo/filters/tables.py
PVGeo/filters/voxelize.py
PVGeo/filters/xyz.py
PVGeo/gmggroup/__init__.py
PVGeo/gmggroup/reader.py
PVGeo/grids/__init__.py
PVGeo/grids/fileio.py
PVGeo/grids/subset.py
PVGeo/grids/transform.py
PVGeo/gslib/__init__.py
PVGeo/gslib/gslib.py
PVGeo/gslib/sgems.py
PVGeo/model_build/__init__.py
PVGeo/model_build/earth.py
PVGeo/model_build/grids.py
PVGeo/readers/__init__.py
PVGeo/readers/binaries.py
PVGeo/readers/delimited.py
PVGeo/ubc/__init__.py
PVGeo/ubc/disc_meshes.py
PVGeo/ubc/general.py
PVGeo/ubc/octree.py
PVGeo/ubc/tensor.py
PVGeo/ubc/two_file_base.py
PVGeo/ubc/write.py
pvgeo-3.0.2.dist-info/licenses/LICENSE
pvgeo-3.0.2.dist-info/METADATA
pvgeo-3.0.2.dist-info/WHEEL
pvgeo-3.0.2.dist-info/top_level.txt
pvgeo-3.0.2.dist-info/RECORD
