Metadata-Version: 2.4
Name: PVGeo
Version: 3.0.2
Summary: Geoscientific visualization tools for PyVista
Home-page: https://github.com/OpenGeoVis/PVGeo
Author: Bane Sullivan
Author-email: info@pvgeo.org
Classifier: Programming Language :: Python
Classifier: License :: OSI Approved :: BSD License
Classifier: Operating System :: OS Independent
Classifier: Topic :: Scientific/Engineering
Classifier: Topic :: Scientific/Engineering :: Visualization
Classifier: Topic :: Scientific/Engineering :: GIS
Classifier: Intended Audience :: Science/Research
Classifier: Natural Language :: English
Requires-Python: >=3.9
License-File: LICENSE
Requires-Dist: numpy>=1.13
Requires-Dist: scipy>=1.1
Requires-Dist: pandas>=0.23.4
Requires-Dist: espatools>=0.0.8
Requires-Dist: pyvista>=0.20.1
Requires-Dist: vtk<9.4,>=8.1
Provides-Extra: pyproj
Requires-Dist: pyproj>=1.9; extra == "pyproj"
Provides-Extra: omf
Requires-Dist: omf>=0.9.3; extra == "omf"
Requires-Dist: omfvista>=0.2.0; extra == "omf"
Provides-Extra: discretize
Requires-Dist: discretize>=0.3.8; extra == "discretize"
Provides-Extra: examples
Requires-Dist: pooch; extra == "examples"
Dynamic: author
Dynamic: author-email
Dynamic: classifier
Dynamic: description
Dynamic: description-content-type
Dynamic: home-page
Dynamic: license-file
Dynamic: provides-extra
Dynamic: requires-dist
Dynamic: requires-python
Dynamic: summary
